mcstastox/LoadFile.py
mcstastox/ReadNeXus.py
mcstastox/__init__.py
mcstastox/_version.py
mcstastox-0.0.11.dist-info/licenses/LICENSE
mcstastox-0.0.11.dist-info/METADATA
mcstastox-0.0.11.dist-info/WHEEL
mcstastox-0.0.11.dist-info/top_level.txt
mcstastox-0.0.11.dist-info/RECORD
