Metadata-Version: 2.4
Name: mcstastox
Version: 0.0.11
Summary: Tool to read McStas NeXus data and export contained information
Author: Mads Bertelsen
License: BSD-3-Clause
Requires-Python: >=3.8
License-File: LICENSE
Requires-Dist: h5py
Requires-Dist: numpy
Provides-Extra: scipp
Requires-Dist: scipp; extra == "scipp"
Dynamic: license-file
